divcalc/__init__.py
divbasiccalculator-0.0.4.dist-info/METADATA
divbasiccalculator-0.0.4.dist-info/WHEEL
divbasiccalculator-0.0.4.dist-info/top_level.txt
divbasiccalculator-0.0.4.dist-info/RECORD
