Metadata-Version: 2.1
Name: divbasiccalculator
Version: 0.0.4
Summary: A very basic calculator
Home-page: UNKNOWN
Author: Divit Kanath
Author-email: divitkanath@gmail.com
License: MIT
Keywords: calculator
Platform: UNKNOWN
Classifier: Development Status :: 5 - Production/Stable
Classifier: Intended Audience :: Education
Classifier: Operating System :: Unix
Classifier: License :: OSI Approved :: MIT License
Classifier: Programming Language :: Python :: 3
